[
    {
        "container_type": "Publication",
        "source": "AUTHOR_PUBLICATION_ENTRY",
        "bib": {
            "title": "Phytochromes function as thermosensors in Arabidopsis",
            "pub_year": "2016",
            "citation": "Science 354 (6314), 886-889, 2016"
        },
        "filled": false,
        "author_pub_id": "w6pSNyEAAAAJ:roLk4NBRz8UC",
        "num_citations": 704,
        "citedby_url": "https://scholar.google.com/scholar?oi=bibs&hl=en&cites=265221557585787237",
        "cites_id": [
            "265221557585787237"
        ]
    },
    {
        "container_type": "Publication",
        "source": "AUTHOR_PUBLICATION_ENTRY",
        "bib": {
            "title": "ELF3 controls thermoresponsive growth in Arabidopsis",
            "pub_year": "2015",
            "citation": "Current biology 25 (2), 194-199, 2015"
        },
        "filled": false,
        "author_pub_id": "w6pSNyEAAAAJ:YsMSGLbcyi4C",
        "num_citations": 231,
        "citedby_url": "https://scholar.google.com/scholar?oi=bibs&hl=en&cites=16910043034756121216",
        "cites_id": [
            "16910043034756121216"
        ]
    },
    {
        "container_type": "Publication",
        "source": "AUTHOR_PUBLICATION_ENTRY",
        "bib": {
            "title": "Coordination of robust single cell rhythms in the Arabidopsis circadian clock via spatial waves of gene expression",
            "pub_year": "2018",
            "citation": "Elife 7, e31700, 2018"
        },
        "filled": false,
        "author_pub_id": "w6pSNyEAAAAJ:5nxA0vEk-isC",
        "num_citations": 91,
        "citedby_url": "https://scholar.google.com/scholar?oi=bibs&hl=en&cites=14677954800664167450",
        "cites_id": [
            "14677954800664167450"
        ]
    },
    {
        "container_type": "Publication",
        "source": "AUTHOR_PUBLICATION_ENTRY",
        "bib": {
            "title": "Network balance via CRY signalling controls the Arabidopsis circadian clock over ambient temperatures",
            "pub_year": "2013",
            "citation": "Molecular systems biology 9 (1), 650, 2013"
        },
        "filled": false,
        "author_pub_id": "w6pSNyEAAAAJ:Tyk-4Ss8FVUC",
        "num_citations": 82,
        "citedby_url": "https://scholar.google.com/scholar?oi=bibs&hl=en&cites=15893857544055497019",
        "cites_id": [
            "15893857544055497019"
        ]
    },
    {
        "container_type": "Publication",
        "source": "AUTHOR_PUBLICATION_ENTRY",
        "bib": {
            "title": "Bistability and oscillations in chemical reaction networks",
            "pub_year": "2009",
            "citation": "Journal of Mathematical Biology 59, 467-501, 2009"
        },
        "filled": false,
        "author_pub_id": "w6pSNyEAAAAJ:MXK_kJrjxJIC",
        "num_citations": 55,
        "citedby_url": "https://scholar.google.com/scholar?oi=bibs&hl=en&cites=7131902819566171147",
        "cites_id": [
            "7131902819566171147"
        ]
    },
    {
        "container_type": "Publication",
        "source": "AUTHOR_PUBLICATION_ENTRY",
        "bib": {
            "title": "Bistability and oscillations in chemical reaction networks",
            "pub_year": "2009",
            "citation": "Journal of Mathematical Biology 59, 467-501, 2009"
        },
        "filled": false,
        "author_pub_id": "w6pSNyEAAAAJ:u-x6o8ySG0sC",
        "num_citations": 55,
        "citedby_url": "https://scholar.google.com/scholar?oi=bibs&hl=en&cites=7131902819566171147",
        "cites_id": [
            "7131902819566171147"
        ]
    },
    {
        "container_type": "Publication",
        "source": "AUTHOR_PUBLICATION_ENTRY",
        "bib": {
            "title": "Coordinated circadian timing through the integration of local inputs in Arabidopsis thaliana",
            "pub_year": "2019",
            "citation": "PLoS biology 17 (8), e3000407, 2019"
        },
        "filled": false,
        "author_pub_id": "w6pSNyEAAAAJ:YOwf2qJgpHMC",
        "num_citations": 48,
        "citedby_url": "https://scholar.google.com/scholar?oi=bibs&hl=en&cites=14064037726242394746",
        "cites_id": [
            "14064037726242394746"
        ]
    },
    {
        "container_type": "Publication",
        "source": "AUTHOR_PUBLICATION_ENTRY",
        "bib": {
            "title": "ELONGATED HYPOCOTYL 5 mediates blue light signalling to the Arabidopsis circadian clock",
            "pub_year": "2018",
            "citation": "The Plant Journal 96 (6), 1242-1254, 2018"
        },
        "filled": false,
        "author_pub_id": "w6pSNyEAAAAJ:KlAtU1dfN6UC",
        "num_citations": 45,
        "citedby_url": "https://scholar.google.com/scholar?oi=bibs&hl=en&cites=9805089827280762961",
        "cites_id": [
            "9805089827280762961"
        ]
    },
    {
        "container_type": "Publication",
        "source": "AUTHOR_PUBLICATION_ENTRY",
        "bib": {
            "title": "Graph theory and qualitative analysis of reaction networks",
            "pub_year": "2008",
            "citation": "Networks and heterogeneous media 3 (2), 295, 2008"
        },
        "filled": false,
        "author_pub_id": "w6pSNyEAAAAJ:u5HHmVD_uO8C",
        "num_citations": 39,
        "citedby_url": "https://scholar.google.com/scholar?oi=bibs&hl=en&cites=4433966467247728627",
        "cites_id": [
            "4433966467247728627"
        ]
    },
    {
        "container_type": "Publication",
        "source": "AUTHOR_PUBLICATION_ENTRY",
        "bib": {
            "title": "Dynamical probing of the mechanisms underlying calcium oscillations",
            "pub_year": "2006",
            "citation": "Journal of Nonlinear Science 16, 483-506, 2006"
        },
        "filled": false,
        "author_pub_id": "w6pSNyEAAAAJ:d1gkVwhDpl0C",
        "num_citations": 28,
        "citedby_url": "https://scholar.google.com/scholar?oi=bibs&hl=en&cites=11318775843362618447",
        "cites_id": [
            "11318775843362618447"
        ]
    },
    {
        "container_type": "Publication",
        "source": "AUTHOR_PUBLICATION_ENTRY",
        "bib": {
            "title": "Fine tuning of hormonal signaling is linked to dormancy status in sweet cherry flower buds",
            "pub_year": "2021",
            "citation": "Tree Physiology 41 (4), 544-561, 2021"
        },
        "filled": false,
        "author_pub_id": "w6pSNyEAAAAJ:hC7cP41nSMkC",
        "num_citations": 21,
        "citedby_url": "https://scholar.google.com/scholar?oi=bibs&hl=en&cites=13109329577564432457",
        "cites_id": [
            "13109329577564432457"
        ]
    },
    {
        "container_type": "Publication",
        "source": "AUTHOR_PUBLICATION_ENTRY",
        "bib": {
            "title": "The interaction graph structure of mass-action reaction networks",
            "pub_year": "2012",
            "citation": "Journal of Mathematical Biology 65, 375-402, 2012"
        },
        "filled": false,
        "author_pub_id": "w6pSNyEAAAAJ:9yKSN-GCB0IC",
        "num_citations": 20,
        "citedby_url": "https://scholar.google.com/scholar?oi=bibs&hl=en&cites=13657079928557473024",
        "cites_id": [
            "13657079928557473024"
        ]
    },
    {
        "container_type": "Publication",
        "source": "AUTHOR_PUBLICATION_ENTRY",
        "bib": {
            "title": "Balance equations can buffer noisy and sustained environmental perturbations of circadian clocks",
            "pub_year": "2011",
            "citation": "Interface Focus 1 (1), 177-186, 2011"
        },
        "filled": false,
        "author_pub_id": "w6pSNyEAAAAJ:2osOgNQ5qMEC",
        "num_citations": 19,
        "citedby_url": "https://scholar.google.com/scholar?oi=bibs&hl=en&cites=8032958781830007058",
        "cites_id": [
            "8032958781830007058"
        ]
    },
    {
        "container_type": "Publication",
        "source": "AUTHOR_PUBLICATION_ENTRY",
        "bib": {
            "title": "Hormonal balance finely tunes dormancy status in sweet cherry flower buds",
            "pub_year": "2018",
            "citation": "BioRxiv 423871, 2018"
        },
        "filled": false,
        "author_pub_id": "w6pSNyEAAAAJ:kNdYIx-mwKoC",
        "num_citations": 12,
        "citedby_url": "https://scholar.google.com/scholar?oi=bibs&hl=en&cites=10881660606145713347",
        "cites_id": [
            "10881660606145713347"
        ]
    },
    {
        "container_type": "Publication",
        "source": "AUTHOR_PUBLICATION_ENTRY",
        "bib": {
            "title": "PeTTSy: a computational tool for perturbation analysis of complex systems biology models",
            "pub_year": "2016",
            "citation": "BMC bioinformatics 17, 1-19, 2016"
        },
        "filled": false,
        "author_pub_id": "w6pSNyEAAAAJ:LkGwnXOMwfcC",
        "num_citations": 10,
        "citedby_url": "https://scholar.google.com/scholar?oi=bibs&hl=en&cites=8028694697256851862",
        "cites_id": [
            "8028694697256851862"
        ]
    },
    {
        "container_type": "Publication",
        "source": "AUTHOR_PUBLICATION_ENTRY",
        "bib": {
            "title": "Using constraints and their value for optimization of large ODE systems",
            "pub_year": "2015",
            "citation": "Journal of the Royal Society Interface 12 (104), 20141303, 2015"
        },
        "filled": false,
        "author_pub_id": "w6pSNyEAAAAJ:WF5omc3nYNoC",
        "num_citations": 8,
        "citedby_url": "https://scholar.google.com/scholar?oi=bibs&hl=en&cites=17037473401875156390",
        "cites_id": [
            "17037473401875156390"
        ]
    },
    {
        "container_type": "Publication",
        "source": "AUTHOR_PUBLICATION_ENTRY",
        "bib": {
            "title": "What are... some graphs of chemical reaction networks?",
            "pub_year": "2008",
            "citation": "Mathematics Institute, University of Warwick, Coventry CV4 7AL, United \u2026, 2008"
        },
        "filled": false,
        "author_pub_id": "w6pSNyEAAAAJ:IjCSPb-OGe4C",
        "num_citations": 4,
        "citedby_url": "https://scholar.google.com/scholar?oi=bibs&hl=en&cites=1829734872808425008",
        "cites_id": [
            "1829734872808425008"
        ]
    },
    {
        "container_type": "Publication",
        "source": "AUTHOR_PUBLICATION_ENTRY",
        "bib": {
            "title": "The interaction graph structure of mass-action reaction networks",
            "pub_year": "2011",
            "citation": "Journal of Mathematical Biology, 2011"
        },
        "filled": false,
        "author_pub_id": "w6pSNyEAAAAJ:_FxGoFyzp5QC",
        "num_citations": 3,
        "citedby_url": "https://scholar.google.com/scholar?oi=bibs&hl=en&cites=5655803341989579424",
        "cites_id": [
            "5655803341989579424"
        ]
    },
    {
        "container_type": "Publication",
        "source": "AUTHOR_PUBLICATION_ENTRY",
        "bib": {
            "title": "Mathematical aspects of chemical reaction networks",
            "pub_year": "2008",
            "citation": "University of Warwick, 2008"
        },
        "filled": false,
        "author_pub_id": "w6pSNyEAAAAJ:UeHWp8X0CEIC",
        "num_citations": 3,
        "citedby_url": "https://scholar.google.com/scholar?oi=bibs&hl=en&cites=14555796738154236987",
        "cites_id": [
            "14555796738154236987"
        ]
    },
    {
        "container_type": "Publication",
        "source": "AUTHOR_PUBLICATION_ENTRY",
        "bib": {
            "title": "Introduction to MATLAB for Biologists",
            "pub_year": "2019",
            "citation": ""
        },
        "filled": false,
        "author_pub_id": "w6pSNyEAAAAJ:_kc_bZDykSQC",
        "num_citations": 2,
        "citedby_url": "https://scholar.google.com/scholar?oi=bibs&hl=en&cites=12172280319394870309",
        "cites_id": [
            "12172280319394870309"
        ]
    },
    {
        "container_type": "Publication",
        "source": "AUTHOR_PUBLICATION_ENTRY",
        "bib": {
            "title": "A definition of cellular interface problems",
            "pub_year": "2009",
            "citation": "Membrane Computing: 9th International Workshop, WMC 2008, Edinburgh, UK \u2026, 2009"
        },
        "filled": false,
        "author_pub_id": "w6pSNyEAAAAJ:qjMakFHDy7sC",
        "num_citations": 2,
        "citedby_url": "https://scholar.google.com/scholar?oi=bibs&hl=en&cites=13501076441268358933",
        "cites_id": [
            "13501076441268358933"
        ]
    },
    {
        "container_type": "Publication",
        "source": "AUTHOR_PUBLICATION_ENTRY",
        "bib": {
            "title": "Multi-Disciplinary Approaches to Plant Responses to Climate Change",
            "pub_year": "2022",
            "citation": "Frontiers in Plant Science 13, 876432, 2022"
        },
        "filled": false,
        "author_pub_id": "w6pSNyEAAAAJ:HDshCWvjkbEC",
        "num_citations": 1,
        "citedby_url": "https://scholar.google.com/scholar?oi=bibs&hl=en&cites=17488612647397990404",
        "cites_id": [
            "17488612647397990404"
        ]
    },
    {
        "container_type": "Publication",
        "source": "AUTHOR_PUBLICATION_ENTRY",
        "bib": {
            "title": "NRF2/KEAP1 pathway is required to fine-tune circadian oscillations as part of the negative feedback loop of the molecular clock: implications for tissue homeostasis and \u2026",
            "pub_year": "2021",
            "citation": "Free Radical Biology and Medicine 177, S58, 2021"
        },
        "filled": false,
        "author_pub_id": "w6pSNyEAAAAJ:mB3voiENLucC",
        "num_citations": 0
    },
    {
        "container_type": "Publication",
        "source": "AUTHOR_PUBLICATION_ENTRY",
        "bib": {
            "title": "Transcriptomic profiles highlight the role of ABA signalling in the regulation of sweet cherry flower bud dormancy",
            "pub_year": "2020",
            "citation": "10th International Rosaceae Genomics Conference (RGC 10), 2020"
        },
        "filled": false,
        "author_pub_id": "w6pSNyEAAAAJ:hFOr9nPyWt4C",
        "num_citations": 0
    },
    {
        "container_type": "Publication",
        "source": "AUTHOR_PUBLICATION_ENTRY",
        "bib": {
            "title": "Exploring Built-In Functions",
            "pub_year": "2019",
            "citation": "Introduction to MATLAB\u00ae for Biologists, 69-84, 2019"
        },
        "filled": false,
        "author_pub_id": "w6pSNyEAAAAJ:dhFuZR0502QC",
        "num_citations": 0
    },
    {
        "container_type": "Publication",
        "source": "AUTHOR_PUBLICATION_ENTRY",
        "bib": {
            "title": "The Basics Using the Command Line",
            "pub_year": "2019",
            "citation": "Introduction to MATLAB\u00ae for Biologists, 7-18, 2019"
        },
        "filled": false,
        "author_pub_id": "w6pSNyEAAAAJ:QIV2ME_5wuYC",
        "num_citations": 0
    },
    {
        "container_type": "Publication",
        "source": "AUTHOR_PUBLICATION_ENTRY",
        "bib": {
            "title": "Importing and Exporting Data",
            "pub_year": "2019",
            "citation": "Introduction to MATLAB\u00ae for Biologists, 129-151, 2019"
        },
        "filled": false,
        "author_pub_id": "w6pSNyEAAAAJ:9ZlFYXVOiuMC",
        "num_citations": 0
    },
    {
        "container_type": "Publication",
        "source": "AUTHOR_PUBLICATION_ENTRY",
        "bib": {
            "title": "Creating Separate Function Files",
            "pub_year": "2019",
            "citation": "Introduction to MATLAB\u00ae for Biologists, 115-127, 2019"
        },
        "filled": false,
        "author_pub_id": "w6pSNyEAAAAJ:mVmsd5A6BfQC",
        "num_citations": 0
    },
    {
        "container_type": "Publication",
        "source": "AUTHOR_PUBLICATION_ENTRY",
        "bib": {
            "title": "MATLAB\u00ae as a Programming Language",
            "pub_year": "2019",
            "citation": "Introduction to MATLAB\u00ae for Biologists, 153-170, 2019"
        },
        "filled": false,
        "author_pub_id": "w6pSNyEAAAAJ:Wp0gIr-vW9MC",
        "num_citations": 0
    },
    {
        "container_type": "Publication",
        "source": "AUTHOR_PUBLICATION_ENTRY",
        "bib": {
            "title": "Anonymous Functions",
            "pub_year": "2019",
            "citation": "Introduction to MATLAB\u00ae for Biologists, 105-114, 2019"
        },
        "filled": false,
        "author_pub_id": "w6pSNyEAAAAJ:4DMP91E08xMC",
        "num_citations": 0
    },
    {
        "container_type": "Publication",
        "source": "AUTHOR_PUBLICATION_ENTRY",
        "bib": {
            "title": "Accessing Help",
            "pub_year": "2019",
            "citation": "Introduction to MATLAB\u00ae for Biologists, 59-68, 2019"
        },
        "filled": false,
        "author_pub_id": "w6pSNyEAAAAJ:aqlVkmm33-oC",
        "num_citations": 0
    },
    {
        "container_type": "Publication",
        "source": "AUTHOR_PUBLICATION_ENTRY",
        "bib": {
            "title": "Writing Script Files",
            "pub_year": "2019",
            "citation": "Introduction to MATLAB\u00ae for Biologists, 39-57, 2019"
        },
        "filled": false,
        "author_pub_id": "w6pSNyEAAAAJ:qxL8FJ1GzNcC",
        "num_citations": 0
    },
    {
        "container_type": "Publication",
        "source": "AUTHOR_PUBLICATION_ENTRY",
        "bib": {
            "title": "Arrays and Matrices",
            "pub_year": "2019",
            "citation": "Introduction to MATLAB\u00ae for Biologists, 19-37, 2019"
        },
        "filled": false,
        "author_pub_id": "w6pSNyEAAAAJ:M3ejUd6NZC8C",
        "num_citations": 0
    },
    {
        "container_type": "Publication",
        "source": "AUTHOR_PUBLICATION_ENTRY",
        "bib": {
            "title": "Graphs and Plots",
            "pub_year": "2019",
            "citation": "Introduction to MATLAB\u00ae for Biologists, 85-104, 2019"
        },
        "filled": false,
        "author_pub_id": "w6pSNyEAAAAJ:4TOpqqG69KYC",
        "num_citations": 0
    },
    {
        "container_type": "Publication",
        "source": "AUTHOR_PUBLICATION_ENTRY",
        "bib": {
            "title": "Research Data supporting Coordination of robust single cell rhythms in the Arabidopsis circadian clock via spatial waves of gene expression",
            "pub_year": "2018",
            "citation": ""
        },
        "filled": false,
        "author_pub_id": "w6pSNyEAAAAJ:3fE2CSJIrl8C",
        "num_citations": 0
    },
    {
        "container_type": "Publication",
        "source": "AUTHOR_PUBLICATION_ENTRY",
        "bib": {
            "title": "Phytochromes function as thermosensors in ",
            "pub_year": "2016",
            "citation": "American Association for the Advancement of Science, 2016"
        },
        "filled": false,
        "author_pub_id": "w6pSNyEAAAAJ:UebtZRa9Y70C",
        "num_citations": 0
    },
    {
        "container_type": "Publication",
        "source": "AUTHOR_PUBLICATION_ENTRY",
        "bib": {
            "title": "Supplementary Information for\u201d PeTSSy: a computational tool for perturbation analysis of complex systems biology models\u201d",
            "pub_year": "2015",
            "citation": ""
        },
        "filled": false,
        "author_pub_id": "w6pSNyEAAAAJ:R3hNpaxXUhUC",
        "num_citations": 0
    },
    {
        "container_type": "Publication",
        "source": "AUTHOR_PUBLICATION_ENTRY",
        "bib": {
            "title": "Mathematical modelling of the plant circadian clock",
            "pub_year": "2014",
            "citation": "9th European Conference on Mathematical and Theoretical Biology, 2014"
        },
        "filled": false,
        "author_pub_id": "w6pSNyEAAAAJ:ZeXyd9-uunAC",
        "num_citations": 0
    },
    {
        "container_type": "Publication",
        "source": "AUTHOR_PUBLICATION_ENTRY",
        "bib": {
            "title": "Temperature-sensitive version of P2010 Arabidopsis clock model by Mirela Domijan, from Gould et al. 2013.",
            "pub_year": "2013",
            "citation": ""
        },
        "filled": false,
        "author_pub_id": "w6pSNyEAAAAJ:-f6ydRqryjwC",
        "num_citations": 0
    },
    {
        "container_type": "Publication",
        "source": "AUTHOR_PUBLICATION_ENTRY",
        "bib": {
            "title": "Supplementary information for Balance equations can buffer",
            "pub_year": "2010",
            "citation": ""
        },
        "filled": false,
        "author_pub_id": "w6pSNyEAAAAJ:hqOjcs7Dif8C",
        "num_citations": 0
    },
    {
        "container_type": "Publication",
        "source": "AUTHOR_PUBLICATION_ENTRY",
        "bib": {
            "title": "Single-molecule DNA mapping",
            "pub_year": "2010",
            "citation": "Health 7, 3657-3703, 2010"
        },
        "filled": false,
        "author_pub_id": "w6pSNyEAAAAJ:8k81kl-MbHgC",
        "num_citations": 0
    },
    {
        "container_type": "Publication",
        "source": "AUTHOR_PUBLICATION_ENTRY",
        "bib": {
            "title": "Stoichiometric network analysis and graph theoretic methods for studying spatial models of chemical reaction networks",
            "pub_year": "2008",
            "citation": "Society for Mathematical Biology Conference, 2008"
        },
        "filled": false,
        "author_pub_id": "w6pSNyEAAAAJ:zYLM7Y9cAGgC",
        "num_citations": 0
    },
    {
        "container_type": "Publication",
        "source": "AUTHOR_PUBLICATION_ENTRY",
        "bib": {
            "title": "Local Indicators of Spatial Association (LISA) and Their Application to Circadian Spatio-Temporal Data",
            "citation": ""
        },
        "filled": false,
        "author_pub_id": "w6pSNyEAAAAJ:TQgYirikUcIC",
        "num_citations": 0
    },
    {
        "container_type": "Publication",
        "source": "AUTHOR_PUBLICATION_ENTRY",
        "bib": {
            "title": "Natural variation in ELF3 controls thermoresponsive growth in Arabidopsis",
            "citation": "CURRENT-BIOLOGY 500, 14-00888R1, 0"
        },
        "filled": false,
        "author_pub_id": "w6pSNyEAAAAJ:Zph67rFs4hoC",
        "num_citations": 0
    },
    {
        "container_type": "Publication",
        "source": "AUTHOR_PUBLICATION_ENTRY",
        "bib": {
            "title": "Supplemental Information ELF3 Controls Thermoresponsive Growth in Arabidopsis",
            "citation": ""
        },
        "filled": false,
        "author_pub_id": "w6pSNyEAAAAJ:ufrVoPGSRksC",
        "num_citations": 0
    },
    {
        "container_type": "Publication",
        "source": "AUTHOR_PUBLICATION_ENTRY",
        "bib": {
            "title": "Supplemental Information for",
            "citation": ""
        },
        "filled": false,
        "author_pub_id": "w6pSNyEAAAAJ:Y0pCki6q_DkC",
        "num_citations": 0
    }
]